calansayt/__init__.py
calansayt/pink.py
calansayt-0.1.0.dist-info/METADATA
calansayt-0.1.0.dist-info/WHEEL
calansayt-0.1.0.dist-info/top_level.txt
calansayt-0.1.0.dist-info/RECORD
