Metadata-Version: 2.4
Name: calansayt
Version: 0.1.0
Summary: Add your description here
Requires-Python: >=3.13
Requires-Dist: cowsay>=6.1
Requires-Dist: matplotlib>=3.10.3
